README.md
setup.cfg
setup.py
chainermn/__init__.py
chainermn/global_except_hook.py
chainermn/nccl.py
chainermn/optimizers.py
chainermn.egg-info/PKG-INFO
chainermn.egg-info/SOURCES.txt
chainermn.egg-info/dependency_links.txt
chainermn.egg-info/requires.txt
chainermn.egg-info/top_level.txt
chainermn/communicators/__init__.py
chainermn/communicators/_communication_utility.py
chainermn/communicators/_memory_utility.py
chainermn/communicators/communicator_base.py
chainermn/communicators/dummy_communicator.py
chainermn/communicators/flat_communicator.py
chainermn/communicators/hierarchical_communicator.py
chainermn/communicators/mpi_communicator_base.py
chainermn/communicators/naive_communicator.py
chainermn/communicators/non_cuda_aware_communicator.py
chainermn/communicators/pure_nccl_communicator.py
chainermn/communicators/single_node_communicator.py
chainermn/communicators/two_dimensional_communicator.py
chainermn/datasets/__init__.py
chainermn/datasets/empty_dataset.py
chainermn/datasets/scatter_dataset.py
chainermn/extensions/__init__.py
chainermn/extensions/allreduce_persistent.py
chainermn/extensions/checkpoint.py
chainermn/extensions/multi_node_evaluator.py
chainermn/functions/__init__.py
chainermn/functions/batch_normalization.py
chainermn/functions/collective_communication.py
chainermn/functions/point_to_point_communication.py
chainermn/functions/pseudo_connect.py
chainermn/iterators/__init__.py
chainermn/iterators/multi_node_iterator.py
chainermn/links/__init__.py
chainermn/links/batch_normalization.py
chainermn/links/multi_node_chain_list.py
chainermn/links/n_step_rnn.py