Metadata-Version: 1.0
Name: chainermn
Version: 1.3.1
Summary: ChainerMN: Multi-node distributed training with Chainer
Home-page: UNKNOWN
Author: Takuya Akiba
Author-email: akiba@preferred.jp
License: UNKNOWN
Platform: UNKNOWN
